steck.py
steck-0.8.0.dist-info/LICENSE
steck-0.8.0.dist-info/METADATA
steck-0.8.0.dist-info/WHEEL
steck-0.8.0.dist-info/entry_points.txt
steck-0.8.0.dist-info/RECORD
