Metadata-Version: 2.1
Name: steck
Version: 0.8.0
Summary: Client for pinnwand pastebin.
Home-page: https://github.com/supakeen/steck
License: MIT
Keywords: pastebin
Author: supakeen
Author-email: cmdr@supakeen.com
Requires-Python: >=3.8.1,<4
Classifier: License :: OSI Approved :: MIT License
Classifier: Programming Language :: Python
Classifier: Programming Language :: Python :: 3
Classifier: Programming Language :: Python :: 3.9
Classifier: Programming Language :: Python :: 3.10
Classifier: Programming Language :: Python :: 3.11
Classifier: Programming Language :: Python :: 3.12
Classifier: Programming Language :: Python :: 3.13
Requires-Dist: appdirs (>=1.4.3,<2.0.0)
Requires-Dist: click (>=8.0)
Requires-Dist: python-magic (>=0.4.15,<0.5.0)
Requires-Dist: requests (>=2.31.0,<3.0.0)
Requires-Dist: termcolor (>=2.3.0,<3.0.0)
Requires-Dist: toml (>=0.10.0,<0.11.0)
Project-URL: Repository, https://github.com/supakeen/steck
